{
  "channel": "3",
  "tagName": "3.0.0-prerelease.200+2026-07-18",
  "assets": [
    {
      "name": "3.0.0-prerelease.200+2026-07-18-linux.tar.gz",
      "url": "https://github.com/ZQuestClassic/ZQuestClassic/releases/download/3.0.0-prerelease.200%2B2026-07-18/3.0.0-prerelease.200%2B2026-07-18-linux.tar.gz",
      "size": 36978198
    },
    {
      "name": "3.0.0-prerelease.200+2026-07-18-mac.dmg",
      "url": "https://github.com/ZQuestClassic/ZQuestClassic/releases/download/3.0.0-prerelease.200%2B2026-07-18/3.0.0-prerelease.200%2B2026-07-18-mac.dmg",
      "size": 38774781
    },
    {
      "name": "3.0.0-prerelease.200+2026-07-18-windows-x64.zip",
      "url": "https://github.com/ZQuestClassic/ZQuestClassic/releases/download/3.0.0-prerelease.200%2B2026-07-18/3.0.0-prerelease.200%2B2026-07-18-windows-x64.zip",
      "size": 41978549
    },
    {
      "name": "3.0.0-prerelease.200+2026-07-18-windows-x86.zip",
      "url": "https://github.com/ZQuestClassic/ZQuestClassic/releases/download/3.0.0-prerelease.200%2B2026-07-18/3.0.0-prerelease.200%2B2026-07-18-windows-x86.zip",
      "size": 39445071
    }
  ]
}